{"idx":2556,"card_name":"K-패스체크카드","company":"KB국민카드","card_type":"체크","cate":"CHK","brands":"VISA","annual_fee":"국내전용 [없음] / 해외겸용 [없음]","annual_fee_detail":"국내전용(Local) 없음<br>해외겸용(VISA) 없음","pre_month_money":200000,"pre_month_condition":"200,000원","only_online":false,"release_dt":"","card_img":"https://d1c5n4ri2guedi.cloudfront.net/card/2556/card_img/33457/2556card.png","top_benefit":[{"title":"교통","tags":["대중교통","10%","적립"],"logo_url":"https://d1c5n4ri2guedi.cloudfront.net/benefit/5/logo_img/910/ico_traffic.png"},{"title":"생활","tags":["생활서비스","1%","적립"],"logo_url":"https://d1c5n4ri2guedi.cloudfront.net/benefit/154/logo_img/923/ico_life.png"},{"title":"간편결제","tags":["KB Pay 이용 시","1%","추가 적립"],"logo_url":"https://d1c5n4ri2guedi.cloudfront.net/benefit/1/logo_img/747/ico_pay.png"}],"key_benefit":[{"title":"적립","logo_url":"https://d1c5n4ri2guedi.cloudfront.net/benefit/86/logo_img/950/ico_point.png","info":"<!-- 표1 --><p><strong>포인트리 적립 서비스</strong></p><table border=\"0\" cellpadding=\"0\" cellspacing=\"0\" class=\"b-table\" width=\"100%\"><tbody><tr class=\"b-table-top\"><td class=\"b-table-top\">구분</td><td class=\"b-table-top\" colspan=\"2\">세부 영역</td><td class=\"b-table-top\">할인율</td><td class=\"b-table-top\">월 할인한도</td><td class=\"b-table-top\">전월 실적</td></tr><tr><td align=\"center\" class=\"b-table\">대중교통 할인</td><td align=\"center\" colspan=\"2\">버스, 지하철</td><td align=\"center\">10%</td><td align=\"center\">2천점</td><td align=\"center\" rowspan=\"8\">20만원</td></tr><tr><td align=\"center\" class=\"b-table\" rowspan=\"6\">생활서비스 할인</td><td align=\"center\">이동통신요금 자동납부 (SK, KT, LG, LiivM)</td><td align=\"center\" rowspan=\"7\">건당 1만원 이상 이용 시</td><td align=\"center\" rowspan=\"6\">1%</td><td align=\"center\" class=\"b-table-br\" rowspan=\"6\">4천점</td></tr><tr><td align=\"center\" class=\"b-table-br\">커피 업종</td></tr><tr><td align=\"center\" class=\"b-table-br\">약국 업종</td></tr><tr><td align=\"center\" class=\"b-table-br\">편의점 업종</td></tr><tr><td align=\"center\" class=\"b-table-br\">영화(CGV, 롯데시네마)</td></tr><tr><td align=\"center\" class=\"b-table-br\">패스트푸드 업종</td></tr><tr><td align=\"center\" class=\"b-table\">KB Pay 추가할인</td><td align=\"center\">&#39;생활서비스 할인&#39; 영역에서 KB Pay 이용 시 추가할인</td><td align=\"center\">1%</td><td align=\"center\" class=\"b-table-br\">4천점</td></tr><tr><td align=\"center\" class=\"b-table\" colspan=\"4\">합 계</td><td align=\"center\">1만점</td><td align=\"center\">&nbsp;</td></tr></tbody></table><p>- <u>대중교통 : 택시, 시외버스, 고속버스, 공항버스 제외</u></p><p>&nbsp; * 버스/지하철 요금적립은 실제 카드 사용일이 아닌 이용대금명세서 상 기재된 이용일을 기준으로 서비스 제공</p><p>- 실적 유예 제공 : 최초 카드 사용 등록 후 다음 달 말일까지 전월 실적 조건 미달 시에도 서비스 제공</p>"},{"title":"유의사항","logo_url":"https://d1c5n4ri2guedi.cloudfront.net/benefit/28/logo_img/866/ico_note%28%EC%9C%A0%EC%9D%98%EC%82%AC%ED%95%AD%29.png","info":"<p><strong>카드발급</strong></p><p>- 후불교통 체크카드 인터넷 신청은 만 18세 이상부터 가능합니다.</p><p>- 만 12세 이상~만 17세 미만의 인터넷 체크카드 발급 제한 연령 고객은 법정대리인을 통해 영업점에서 체크카드 신청이 가능합니다.</p><p>- 외국인 고객은 고객센터(1588-1688)로 확인하여 주시기 바랍니다.</p><p>- 특수채권 잔액 보유 또는 은행연합회 신용관리 대상 등 일부 고객은 후불교통기능이 탑재된 KB국민 체크카드의 발급이 제한될 수 있습니다.</p><p><br></p><p><strong>전월 이용실적 기준</strong></p><p>- 전월 1일 ~ 말일(승인시점 기준) KB국민 알뜰교통플러스 체크카드 승인(이용)금액</p><p>- 해외이용금액은 전월 1일 ~ 말일까지 매입완료 기준</p><p>- 취소금액은 취소전표가 당사에 접수된 월의 실적에서 차감</p><p><br></p><p><strong>전월 이용실적 제외 대상</strong></p><p>- <u>후불교통요금, 무승인금액(자판기, 터널통행료, 유료도로, 기차/고속버스 취소 반환 수수료 등), 정부지원금 이용금액(보육료, 유치원보조비, 바우처 이용금액 등), 포인트리 충전금액, 대학(대학원) 등록금, 상품권 및 선불카드(선불전자지급수단 포함) 구입(충전) 금액, 연체료, 지방세(지방세, 상하수도, 세외수입), 취소금액, 각종 수수료 및 이자</u></p><p><br></p><p><strong>적립서비스 적용 안내</strong></p><p>- 본인 회원 기준으로 월간 적립한도가 제공되며, 적립 한도는 매월 1일 ~ 말일까지 (승인시점 기준) 이용 금액으로 적용됩니다.</p><p>- 적립서비스는 월간 적립한도 내에서 적립이 적용되며, 잔여 적립한도는 이월되지 않습니다.</p><p>- 적립 받은 매출을 취소한 경우 취소 전표가 실시간 접수되지 않아 적립 한도가 즉시 복원되지 않을 수 있습니다.</p><p>- 업종에 따른 적립 서비스는 대상 가맹점이 KB국민카드의 업종분류기준 상 해당 업종에 한하여 제공합니다.</p><p>- 별도 전용 가맹점번호로 승인되는 PG(결제대행)업체 또는 일부 간편결제(Pay) 이용 시 적립대상에서 제외될 수 있으며, 대행사이트를 통한 결제 및 호텔, 백화점, 대형마트, 철도/역사 등에 입점한 가맹점이나 상품권 구매 시 적립 대상에서 제외될 수 있습니다.</p><p>- <u>상품권 및 선불카드(선불전자지급수단 포함) 구입&middot;충전금액, 연체료, 취소금액의 경우 적립에서 제외됩니다.</u></p><p>- 적립서비스는 제휴업체 정책에 따라 타 적립카드와 중복적립이 제한될 수 있습니다.</p>"}],"benefit_categories":"기타, 대중교통, 편의점, 약국, 영화, 카페, KT, LGU+, SKT, 기타, 패스트푸드","detail_url":"https://www.card-gorilla.com/card/detail/2556","top_benefit_summary":"교통: 대중교통 10% 적립 | 생활: 생활서비스 1% 적립 | 간편결제: KB Pay 이용 시 1% 추가 적립"}